{
  "typography_styles": {
    "theme_engine": {
      "heading": {
        "title_1": {
          "$type": "typography",
          "$value": {
            "fontFamily": "{semantic.typography.fontFamilies.main}",
            "fontWeight": "{semantic.typography.fontWeights.main.semibold.normal}",
            "fontSize": "{semantic.typography.fontSizes.large}",
            "lineHeight": "{semantic.typography.lineHeights.close.large}",
            "letterSpacing": "{semantic.typography.letterSpacings.regular}",
            "paragraphSpacing": "{semantic.dimension.spacing.zero}",
            "paragraphIndent": "{semantic.dimension.spacing.zero}",
            "textCase": "{semantic.typography.textCase.normal}",
            "textDecoration": "{semantic.typography.textDecoration.default}"
          },
          "$description": "Starter typography style generated by theme-engine init."
        }
      },
      "content": {
        "body": {
          "$type": "typography",
          "$value": {
            "fontFamily": "{semantic.typography.fontFamilies.content}",
            "fontWeight": "{semantic.typography.fontWeights.content.regular.normal}",
            "fontSize": "{semantic.typography.fontSizes.medium}",
            "lineHeight": "{semantic.typography.lineHeights.regular.medium}",
            "letterSpacing": "{semantic.typography.letterSpacings.regular}",
            "paragraphSpacing": "{semantic.dimension.spacing.zero}",
            "paragraphIndent": "{semantic.dimension.spacing.zero}",
            "textCase": "{semantic.typography.textCase.normal}",
            "textDecoration": "{semantic.typography.textDecoration.default}"
          },
          "$description": "Starter typography style generated by theme-engine init."
        }
      },
      "display": {
        "hero": {
          "$type": "typography",
          "$value": {
            "fontFamily": "{semantic.typography.fontFamilies.display}",
            "fontWeight": "{semantic.typography.fontWeights.display.bold.normal}",
            "fontSize": "{semantic.typography.fontSizes.tera}",
            "lineHeight": "{semantic.typography.lineHeights.close.tera}",
            "letterSpacing": "{semantic.typography.letterSpacings.regular}",
            "paragraphSpacing": "{semantic.dimension.spacing.zero}",
            "paragraphIndent": "{semantic.dimension.spacing.zero}",
            "textCase": "{semantic.typography.textCase.normal}",
            "textDecoration": "{semantic.typography.textDecoration.default}"
          },
          "$description": "Starter typography style generated by theme-engine init."
        }
      },
      "hierarchy": {
        "eyebrow": {
          "$type": "typography",
          "$value": {
            "fontFamily": "{semantic.typography.fontFamilies.main}",
            "fontWeight": "{semantic.typography.fontWeights.main.semibold.normal}",
            "fontSize": "{semantic.typography.fontSizes.small}",
            "lineHeight": "{semantic.typography.lineHeights.tight.small}",
            "letterSpacing": "{semantic.typography.letterSpacings.regular}",
            "paragraphSpacing": "{semantic.dimension.spacing.zero}",
            "paragraphIndent": "{semantic.dimension.spacing.zero}",
            "textCase": "{semantic.typography.textCase.normal}",
            "textDecoration": "{semantic.typography.textDecoration.default}"
          },
          "$description": "Starter typography style generated by theme-engine init."
        }
      },
      "action": {
        "primary": {
          "$type": "typography",
          "$value": {
            "fontFamily": "{semantic.typography.fontFamilies.main}",
            "fontWeight": "{semantic.typography.fontWeights.main.semibold.normal}",
            "fontSize": "{semantic.typography.fontSizes.medium}",
            "lineHeight": "{semantic.typography.lineHeights.tight.medium}",
            "letterSpacing": "{semantic.typography.letterSpacings.regular}",
            "paragraphSpacing": "{semantic.dimension.spacing.zero}",
            "paragraphIndent": "{semantic.dimension.spacing.zero}",
            "textCase": "{semantic.typography.textCase.normal}",
            "textDecoration": "{semantic.typography.textDecoration.default}"
          },
          "$description": "Starter typography style generated by theme-engine init."
        }
      },
      "link": {
        "default": {
          "$type": "typography",
          "$value": {
            "fontFamily": "{semantic.typography.fontFamilies.main}",
            "fontWeight": "{semantic.typography.fontWeights.main.regular.normal}",
            "fontSize": "{semantic.typography.fontSizes.medium}",
            "lineHeight": "{semantic.typography.lineHeights.tight.medium}",
            "letterSpacing": "{semantic.typography.letterSpacings.regular}",
            "paragraphSpacing": "{semantic.dimension.spacing.zero}",
            "paragraphIndent": "{semantic.dimension.spacing.zero}",
            "textCase": "{semantic.typography.textCase.normal}",
            "textDecoration": "{semantic.typography.textDecoration.underline}"
          },
          "$description": "Starter typography style generated by theme-engine init."
        }
      },
      "code": {
        "inline": {
          "$type": "typography",
          "$value": {
            "fontFamily": "{semantic.typography.fontFamilies.code}",
            "fontWeight": "{semantic.typography.fontWeights.code.regular.normal}",
            "fontSize": "{semantic.typography.fontSizes.small}",
            "lineHeight": "{semantic.typography.lineHeights.tight.small}",
            "letterSpacing": "{semantic.typography.letterSpacings.regular}",
            "paragraphSpacing": "{semantic.dimension.spacing.zero}",
            "paragraphIndent": "{semantic.dimension.spacing.zero}",
            "textCase": "{semantic.typography.textCase.normal}",
            "textDecoration": "{semantic.typography.textDecoration.default}"
          },
          "$description": "Starter typography style generated by theme-engine init."
        }
      }
    }
  }
}